slitlessutils/__init__.py
slitlessutils/_version.py
slitlessutils/config.py
slitlessutils/conftest.py
slitlessutils/info.py
slitlessutils/logger.py
slitlessutils/version.py
slitlessutils/core/__init__.py
slitlessutils/core/modules/__init__.py
slitlessutils/core/modules/module.py
slitlessutils/core/modules/extract/__init__.py
slitlessutils/core/modules/extract/multi/__init__.py
slitlessutils/core/modules/extract/multi/lcurve.py
slitlessutils/core/modules/extract/multi/matrix.py
slitlessutils/core/modules/extract/multi/menger.py
slitlessutils/core/modules/extract/multi/multi.py
slitlessutils/core/modules/extract/multi/optimizer.py
slitlessutils/core/modules/extract/multi/result.py
slitlessutils/core/modules/extract/single/__init__.py
slitlessutils/core/modules/extract/single/contamination.py
slitlessutils/core/modules/extract/single/single.py
slitlessutils/core/modules/group/__init__.py
slitlessutils/core/modules/group/group.py
slitlessutils/core/modules/group/groupcollection.py
slitlessutils/core/modules/region/__init__.py
slitlessutils/core/modules/region/region.py
slitlessutils/core/modules/simulate/__init__.py
slitlessutils/core/modules/simulate/simulate.py
slitlessutils/core/modules/tabulate/__init__.py
slitlessutils/core/modules/tabulate/tabulate.py
slitlessutils/core/photometry/__init__.py
slitlessutils/core/photometry/avefnu.py
slitlessutils/core/photometry/band.py
slitlessutils/core/photometry/sed.py
slitlessutils/core/photometry/throughput.py
slitlessutils/core/preprocess/__init__.py
slitlessutils/core/preprocess/astrometry/__init__.py
slitlessutils/core/preprocess/astrometry/affinetweak.py
slitlessutils/core/preprocess/astrometry/downgrade_wcs.py
slitlessutils/core/preprocess/astrometry/upgrade_wcs.py
slitlessutils/core/preprocess/astrometry/utils.py
slitlessutils/core/preprocess/astrometry/tests/__init__.py
slitlessutils/core/preprocess/astrometry/tests/test_astrometry.py
slitlessutils/core/preprocess/background/__init__.py
slitlessutils-1.0.0.dist-info/LICENSE.rst
slitlessutils-1.0.0.dist-info/METADATA
slitlessutils-1.0.0.dist-info/WHEEL
slitlessutils-1.0.0.dist-info/top_level.txt
slitlessutils-1.0.0.dist-info/RECORD
