Metadata-Version: 2.1
Name: slitlessutils
Version: 1.0.0
Summary: A compendium of tools to analyze slitless spectroscopy
Author-email: Slitlessutils Developers <help@stsci.edu>
License: Copyright (c) 2023, Association of Universities for Research in Astronomy (AURA)
Project-URL: Homepage, https://github.com/spacetelescope/slitlessutils
Project-URL: Documentation, https://slitlessutils.readthedocs.io/en/stable/
Keywords: grism,prism,slitless spectroscopy,HST,WFC3,UVIS,IR,ACS,WFC,SBC,JWST,NIRISS,wide field
Classifier: Intended Audience :: Science/Research
Classifier: License :: OSI Approved :: BSD License
Classifier: Natural Language :: English
Classifier: Operating System :: OS Independent
Classifier: Programming Language :: Python
Classifier: Programming Language :: Python :: 3
Classifier: Topic :: Scientific/Engineering :: Astronomy
Requires-Python: >=3.9
License-File: LICENSE.rst
Requires-Dist: astropy >=5.0.4
Requires-Dist: astroquery
Requires-Dist: drizzlepac
Requires-Dist: h5py >=3.6.0
Requires-Dist: networkx >=2.6.3
Requires-Dist: numpy >=1.22.3
Requires-Dist: matplotlib >=3.5.2
Requires-Dist: pandas >=1.4.2
Requires-Dist: psutil >=5.9.0
Requires-Dist: pypolyclip >=1.0.0
Requires-Dist: pysiaf >=0.16.4
Requires-Dist: scikit-image >=0.19.2
Requires-Dist: scipy >=1.8.0
Requires-Dist: shapely >=1.8.2
Requires-Dist: tqdm >=4.64.0
Provides-Extra: docs
Requires-Dist: sphinx-astropy >=1.6 ; extra == 'docs'
Requires-Dist: sphinx-rtd-theme ; extra == 'docs'
Requires-Dist: tomli ; (python_version < "3.11") and extra == 'docs'
Provides-Extra: test
Requires-Dist: pytest-astropy >=0.10 ; extra == 'test'
